CHANGELOG.md
lucidic/__init__.py
lucidic/main.py
lucidic-0.1.2.dist-info/LICENSE
lucidic-0.1.2.dist-info/WHEEL
lucidic-0.1.2.dist-info/METADATA
lucidic-0.1.2.dist-info/RECORD
